kontrctl/__init__.py
kontrctl/__main__.py
kontrctl/cli.py
kontrctl/commands/__init__.py
kontrctl/commands/auth.py
kontrctl/commands/courses.py
kontrctl/commands/definitions.py
kontrctl/commands/execute.py
kontrctl/commands/general.py
kontrctl/commands/groups.py
kontrctl/commands/logs.py
kontrctl/commands/permissions.py
kontrctl/commands/project_configs.py
kontrctl/commands/projects.py
kontrctl/commands/remotes.py
kontrctl/commands/roles.py
kontrctl/commands/secrets.py
kontrctl/commands/submission_files.py
kontrctl/commands/submissions.py
kontrctl/commands/submit.py
kontrctl/commands/users.py
kontrctl/commands/workers.py
kontrctl/config.py
kontrctl/errors.py
kontrctl/log_config.py
kontrctl/utils/__init__.py
kontrctl/utils/helpers.py
kontrctl-0.6.0.dist-info/entry_points.txt
kontrctl-0.6.0.dist-info/WHEEL
kontrctl-0.6.0.dist-info/METADATA
kontrctl-0.6.0.dist-info/RECORD
